esdrt.content-1.77.4-py2.7-nspkg.pth
esdrt/content/INTEGRATION.txt
esdrt/content/__init__.py
esdrt/content/comment.py
esdrt/content/commentanswer.py
esdrt/content/commentextender.py
esdrt/content/conclusion.py
esdrt/content/conclusionsphase2.py
esdrt/content/configure.zcml
esdrt/content/constants.py
esdrt/content/converter.py
esdrt/content/crf_code_matching.py
esdrt/content/crons.py
esdrt/content/esdrtfile.py
esdrt/content/export_other.py
esdrt/content/indexers.py
esdrt/content/ldap_utils.py
esdrt/content/observation.py
esdrt/content/overrides.zcml
esdrt/content/patches.py
esdrt/content/patches.zcml
esdrt/content/permissions.zcml
esdrt/content/profiles.zcml
esdrt/content/question.py
esdrt/content/reviewfolder.py
esdrt/content/setuphandlers.py
esdrt/content/subscribers.py
esdrt/content/subscriptionconfiguration.py
esdrt/content/tests.py
esdrt/content/timeit.py
esdrt/content/utils.py
esdrt/content/vocabularies.py
esdrt/content/vocabularies.zcml
esdrt/content/adapters/__init__.py
esdrt/content/adapters/configure.zcml
esdrt/content/adapters/reference_number.py
esdrt/content/browser/__init__.py
esdrt/content/browser/attachmentdownload.py
esdrt/content/browser/carryover.py
esdrt/content/browser/comments.py
esdrt/content/browser/configure.zcml
esdrt/content/browser/copyfiles.py
esdrt/content/browser/get_sample_xls.py
esdrt/content/browser/inbox_sections.py
esdrt/content/browser/interfaces.py
esdrt/content/browser/macros.py
esdrt/content/browser/management.py
esdrt/content/browser/observation_import.py
esdrt/content/browser/statechange.py
esdrt/content/browser/statisticsview.py
esdrt/content/browser/tableau.py
esdrt/content/browser/templates/assign_answerer_form.pt
esdrt/content/browser/templates/assign_conclusion_reviewer_form.pt
esdrt/content/browser/templates/assign_counterpart_form.pt
esdrt/content/browser/templates/carryover.pt
esdrt/content/browser/templates/finalisedfolderview.pt
esdrt/content/browser/templates/import_observation.pt
esdrt.content-1.77.4.dist-info/METADATA
esdrt.content-1.77.4.dist-info/WHEEL
esdrt.content-1.77.4.dist-info/entry_points.txt
esdrt.content-1.77.4.dist-info/namespace_packages.txt
esdrt.content-1.77.4.dist-info/top_level.txt
esdrt.content-1.77.4.dist-info/RECORD
