Metadata-Version: 2.1
Name: esdrt.content
Version: 1.77.4
Summary: Content-types for ESD Review Tool
Home-page: https://github.com/eea/esdrt.content/
Author: Mikel Larreategi
Author-email: mlarreategi@codesyntax.com
License: GPL
Platform: UNKNOWN
Classifier: Framework :: Plone
Classifier: Programming Language :: Python
Classifier: Topic :: Software Development :: Libraries :: Python Modules
Requires-Dist: setuptools
Requires-Dist: five.grok
Requires-Dist: plone.app.dexterity[grok,relations]
Requires-Dist: plone.namedfile[blobs]
Requires-Dist: collective.z3cform.datagridfield
Requires-Dist: plone.api
Requires-Dist: Products.ATVocabularyManager
Requires-Dist: plone.app.versioningbehavior
Requires-Dist: plone.app.workflowmanager
Requires-Dist: cs.htmlmailer
Requires-Dist: collective.deletepermission
Requires-Dist: tablib
Requires-Dist: python-docx (==0.8.5)
Requires-Dist: zc.dict
Requires-Dist: collective.monkeypatcher
Requires-Dist: python-ldap
Requires-Dist: Products.LDAPUserFolder
Requires-Dist: openpyxl
Requires-Dist: collective.exportimport
